setup.py
hip2/__init__.py
hip2/reader.py
hip2/star.py
hip2/writer.py
hipparchos2_io.egg-info/PKG-INFO
hipparchos2_io.egg-info/SOURCES.txt
hipparchos2_io.egg-info/dependency_links.txt
hipparchos2_io.egg-info/top_level.txt