Metadata-Version: 1.0
Name: hipparchos2-io
Version: 1.0.2
Summary: A Python library for reading Hipparcos new reduction data, and for writing Hipparcos new reduction data to a CSV.
Home-page: https://github.com/JohnHBrock/hipparchos2-io
Author: John Brock
Author-email: johnhbrock@gmail.com
License: MIT License
Platform: UNKNOWN
